moises/__init__.py
Moises-0.0.9.dist-info/LICENSE
Moises-0.0.9.dist-info/METADATA
Moises-0.0.9.dist-info/WHEEL
Moises-0.0.9.dist-info/top_level.txt
Moises-0.0.9.dist-info/RECORD
