Metadata-Version: 2.1
Name: Moises
Version: 0.0.9
Summary: Moises Python SDK
Author-email: plasticuproject <plasticuproject@pm.me>
Project-URL: Homepage, https://github.com/plasticuproject/moises
Classifier: Programming Language :: Python :: 3
Classifier: License :: OSI Approved :: GNU General Public License v3 (GPLv3)
Classifier: Operating System :: OS Independent
Requires-Python: >=3.9
License-File: LICENSE
